{
    "hook": "https://discordapp.com/api/webhooks/571522057012248598/5NdsVyml-DgAgoBzda20hD7Eup6NILnKrAzjsCBiLftfHmwCJyiTr7leaZaro8IfV7sL",
    "template": {
        "username": "Arin",
        "embeds": [
            {
                "author": {
                    "icon_url": "",
                    "name": "",
                    "url": ""
                },
                "thumbnail": {
                    "url": ""
                },
                "title": "",
                "url": "",
                "description": "",
                "fields": [
                    {
                        "inline": true,
                        "name": "Likes",
                        "value": ""
                    },
                    {
                        "inline": true,
                        "name": "Comments",
                        "value": ""
                    }
                ],
                "image": {
                    "url": ""
                },
                "footer": {
                    "icon_url": "https://images-ext-1.discordapp.net/external/YQAD9qmchw1q9gDTiT9pS_p_PtmTQOV9oWZcvPw_fC4/https/i.imgur.com/7Pe6sAD.png",
                    "text": "Posted on Instagram"
                },
                "timestamp": "",
                "color": 8323327
            }
        ]
    },
    "template2": {
        "image": {
            "url": ""
        },
        "color": 11894492
    },
    "Accounts": {
        "2581471": "taeeunzzang",
        "38566194": "therealminnn",
        "52808004": "miryoakajohoney",
        "186879219": "euna102794",
        "188590089": "kzt__",
        "232000141": "yoni2_",
        "383482884": "eunjung.hahm",
        "408995420": "kimnaris",
        "416769420": "ryuserasera",
        "417837724": "wldnjs62",
        "419955242": "snowbabyq",
        "445716581": "rena_0629",
        "460490422": "blossomh_",
        "484009840": "gyeongree",
        "511958128": "hatfelt",
        "532606451": "ahnhani_92",
        "537501571": "hyeliniseo",
        "548455982": "flashe_narae_ing",
        "566766895": "parang_gaheeeee",
        "578423855": "thesy88",
        "613086263": "moongom119",
        "631683294": "d.gyoung95",
        "642764983": "superstar_jhs",
        "647869935": "dongdong810",
        "655150494": "ninistrickland",
        "657109901": "juminhee",
        "679286354": "pyopyohyemi",
        "712704580": "lzx_candy_s",
        "719848330": "miyayeah",
        "726294623": "hyonile_e",
        "728223543": "rainbow__xu",
        "745039200": "jeonghwa_0508",
        "795050172": "a_0young",
        "804181663": "ysl_ovely",
        "1002140332": "hwajung95",
        "1027760475": "melodysoyani",
        "1097259991": "snowmanloveu",
        "1098519284": "minnnzzii",
        "1171812713": "bacccarat",
        "1189099446": "dahye0612",
        "1209908153": "chloris_mijin",
        "1228021208": "e_gawon_e",
        "1242076576": "luvlyzzy",
        "1250974018": "lee_bo_lim",
        "1258080288": "hiellin",
        "1263307207": "lolol0ps2",
        "1266984002": "bimil_jieun",
        "1271631782": "eunvely_park",
        "1277781915": "woohee91",
        "1302205049": "nalll88",
        "1323423753": "myongd_97",
        "1364448970": "gyul.97",
        "1369621484": "queenkong_kimi",
        "1387566679": "songain87",
        "1401639263": "tahiti__ari",
        "1416436897": "anyewon0210",
        "1418190541": "sanha_4us",
        "1420184024": "chu0s21_",
        "1425058014": "lovesori_",
        "1435125767": "_yoonjo",
        "1456841681": "soh_eee",
        "1463167222": "sooo_pilates",
        "1474898830": "jiyul_7",
        "1506018519": "_misomi__",
        "1507979106": "skuukzky",
        "1509763999": "ha_seo",
        "1531118206": "dalsooobin",
        "1545455453": "hichaheebye",
        "1546702273": "siannnn_s2",
        "1559113799": "hyeri_0609",
        "1569542207": "e_young0816",
        "1584246161": "akmu_suhyun",
        "1677895411": "zuny_l___l",
        "1692800026": "dlwlrma",
        "1704275850": "hami_xiaohan",
        "1725526925": "ssj_3725",
        "1738782834": "jiyeon2__",
        "1755307669": "borabora_sugar",
        "1762374672": "linzy_minji",
        "1764460707": "seola_s",
        "1764466250": "_eunseo_v",
        "1773729536": "wm_ohmygirl",
        "1780070827": "yura_936",
        "1796028992": "young_g_hur",
        "1811762156": "followplayback",
        "1904734094": "drrrr.youkyung",
        "1919546532": "hye_9.9",
        "1919552169": "queenchoa_",
        "1919725725": "hv_u0",
        "1928716259": "mamamoo_official",
        "1967949849": "0.you__",
        "1969954934": "hyyun__171",
        "2000054693": "z_er0rain",
        "2000217364": "eyedi_camp",
        "2051147892": "__shuarune__",
        "2053646255": "yn_s_1230",
        "2054089623": "mwhite_lot",
        "2066540098": "shizuku_030",
        "2076069362": "by.gaeun",
        "2085161279": "love_nca",
        "2092873174": "gaeun_jeon",
        "2098220984": "dananuniii",
        "2099784424": "ayeon3131",
        "2105426093": "dlruru",
        "2106695218": "tashaalow",
        "2107411892": "twicetagram",
        "2112068949": "yesyesyelll",
        "2115113594": "yerin_the_genuine",
        "2162746050": "rui_1oo8",
        "2227823523": "vivian_viviviii",
        "2233045337": "nustaa_",
        "2237843937": "s2onlyone1",
        "2258488053": "hyeona____a",
        "2293070487": "yuseolofficial",
        "2303634035": "official_lvlz8_",
        "2351162584": "_haeyoung_park",
        "2400160020": "one._.dew",
        "2534724824": "shiro36run",
        "2535474654": "mulgokizary",
        "2714774884": "keumjo_1217",
        "2769555098": "yunvely_0824",
        "2920560812": "artist_eunji",
        "2956202295": "baeg524______exoluv",
        "2984499215": "shy_s2_shine",
        "3016722907": "5_2_3__",
        "3062405238": "braveg_yj",
        "3184106250": "yugopa216",
        "3273399155": "rachel__1020",
        "3503308501": "jusilver_67",
        "3550613620": "areum0ju",
        "3686706354": "jessicaleeseul",
        "3839952941": "loonatheworld",
        "3893578138": "mail_yujin",
        "3907715676": "jeonminju94",
        "4012362463": "yoooon_g_",
        "4035970478": "acemax_red_lena",
        "4096234943": "hye_rim_7",
        "4167720175": "chengxiao_0715",
        "4171312592": "i_ampurple",
        "4187929424": "goodnight_dreamcatcher",
        "4192576188": "hf_dreamcatcher",
        "4213563721": "_winniebear_",
        "4699459321": "baejinyea",
        "4699763050": "yudong_0214",
        "4699845069": "hhae_in_",
        "4953595761": "bn_95819",
        "4518181846": "j.a.n.e.c.h.u.n",
        "4678480179": "songjjyu",
        "4699977301": "lsoyeonb",
        "4518878522": "1998_suji_ya",
        "6119630393": "rosee_sun",
        "5872432120": "__yoonbomi__",
        "6372822034": "gowooon_m111",
        "6121458431": "silver_s2_zero",
        "6312169697": "yebin_o3o",
        "6208959605": "silver_rain__917",
        "6248118229": "____jjjjohyuns",
        "4589838539": "somsomi0309",
        "7373003648": "taeha.yoo",
        "4569490895": "eyedi_b_cut",
        "7480990278": "e_lludda",
        "7463763449": "official.khan.ig",
        "7061444027": "hayoungl2",
        "6102497033": "eun_jin3851",
        "8004108750": "roses_are_rosie",
        "8011506095": "sooyaaa__",
        "6938463993": "75_yabuki",
        "5753402370": "10_hitomi_06",
        "8240781834": "jw_so_cute_0627",
        "8293386575": "m.meiqi7",
        "7210829418": "k.minjoo_official",
        "8511782514": "soomleee",
        "7499328084": "s_syni_",
        "9972190259": "kim_reyun",
        "8545597992": "official_sohee",
        "6903025188": "sso_omm2",
        "8012033210": "lalalalisa_m",
        "5791491410": "h_22_j8",
        "7836825987": "silver_chae_526",
        "4311688584": "g_ooseul",
        "7077660623": "yooojin_so",
        "8292821778": "_hongeuijin_",
        "9247914908": "rubyrubyrubiee",
        "8701862336": "flashe_sujin",
        "9293310784": "yukika.kr.official",
        "4796007755": "1003_j",
        "7877656307": "_mogi_shinobu_",
        "5064146055": "myaostagram_380",
        "6632723994": "jin_iny21",
        "6003067932": "truesol__0824",
        "5465862357": "jiwon_0w0",
        "7073588076": "eunjiniayo_",
        "6198974639": "wooooo__a",
        "6097291355": "dayeon_you",
        "6048412305": "909xyb",
        "7164071955": "_____min_jeong",
        "7152157419": "huiwon_blmb",
        "5336033952": "busters_official",
        "7987051784": "nature.nchworld",
        "12544593289": "itzy.all.in.us",
        "6695534373": "cube_clc_official",
        "12406096853": "_p_h_y_98",
        "12893580361": "j_e_w_w_w",
        "9183852095": "0_0.1114",
        "1582044635": "redvelvet.smtown",
        "13031767803": "hyeri.official",
        "4942676231": "officialfromis_9",
        "5264578501": "hunus_elris",
        "13766353325": "nayoung_lim95",
        "9727984593": "official_everglow",
        "1595513758": "rothy_ming",
        "14015330998": "_imyour_joy",
        "8337946023": "high_school_haebin",
        "14352660181": "yyyyeeun",
        "9224392067": "seung_monkey",
        "39456180": "chongtingyanelkie",
        "14646456220": "superb_ean",
        "14693608754": "utokki_",
        "14400214942": "hi_sseulgi",
        "8505683794": "official_izone"
    }
}